ZeepLibrary/__init__.py
ZeepLibrary/zeeplibrary.py
robotframework_zeeplibrary-0.9.2.dist-info/METADATA
robotframework_zeeplibrary-0.9.2.dist-info/WHEEL
robotframework_zeeplibrary-0.9.2.dist-info/top_level.txt
robotframework_zeeplibrary-0.9.2.dist-info/RECORD
