Metadata-Version: 2.1
Name: robotframework-zeeplibrary
Version: 0.9.2
Summary: Robot Framework library for using Zeep.
Home-page: https://github.com/bartkl/robotframework-zeeplibrary
Author: Bart Kleijngeld
Author-email: bartkl@gmail.com
License: UNKNOWN
Platform: UNKNOWN
Classifier: Operating System :: OS Independent
Requires-Dist: zeep (>=2.5.0)
